shipstation_sdk/__init__.py
shipstation_sdk/client.py
shipstation_sdk/models.py
shipstation_sdk/parameters.py
shipstation_sdk/py.typed
idi_shipstation_sdk-0.8.0.dist-info/WHEEL
idi_shipstation_sdk-0.8.0.dist-info/METADATA
idi_shipstation_sdk-0.8.0.dist-info/RECORD
