Metadata-Version: 2.3
Name: idi-shipstation-sdk
Version: 0.8.0
Summary: ShipStation API SDK
Author: Bradley Reynolds
Author-email: Bradley Reynolds <bradley.reynolds@impressdesigns.com>
License: MIT
Requires-Dist: pydantic>=2.9.2
Requires-Dist: httpx>=0.27.2
Requires-Python: >=3.13
Project-URL: repository, https://github.com/impressdesigns/shipstation-sdk/
Project-URL: documentation, https://impressdesigns.dev/shipstation-sdk/
